shadcn_django/__init__.py
shadcn_django/__main__.py
shadcn_django/add.py
shadcn_django/components.py
shadcn_django/console.py
shadcn_django/constants.py
shadcn_django/initialize.py
shadcn_django/list.py
shadcn_django/main.py
shadcn_django-0.23.0.dist-info/METADATA
shadcn_django-0.23.0.dist-info/WHEEL
shadcn_django-0.23.0.dist-info/entry_points.txt
shadcn_django-0.23.0.dist-info/licenses/LICENSE
shadcn_django-0.23.0.dist-info/RECORD
