Metadata-Version: 2.4
Name: shadcn_django
Version: 0.23.0
Summary: shadcn/ui for Django
Author-email: Sarthak Jariwala <sarthak@sarthakjariwala.com>
License-File: LICENSE
Keywords: components,django,shadcn,shadcn-django,shadcnui,ui
Classifier: Environment :: Web Environment
Classifier: Framework :: Django
Classifier: Intended Audience :: Developers
Classifier: License :: OSI Approved :: MIT License
Classifier: Operating System :: OS Independent
Classifier: Programming Language :: Python :: 3
Classifier: Topic :: Software Development :: Libraries :: Application Frameworks
Classifier: Topic :: Software Development :: Libraries :: Python Modules
Classifier: Topic :: Software Development :: User Interfaces
Requires-Python: >=3.12
Requires-Dist: copier>=9.5.0
Requires-Dist: typer>=0.15.1
